{"ms-python.python":{"InterpreterSelectionTip":true},"googlecloudtools.cloudcode":{"cloudcode.session-index":{"dateStr":"20211111","counter":5}},"golang.go":{"go.extensionVersion":"0.22.0","forceUpdateForGoplsOnDefault":{"options":{},"loose":false,"includePrerelease":false,"raw":"0.6.4","major":0,"minor":6,"patch":4,"prerelease":[],"build":[],"version":"0.6.4"},"toolsGoInfo":{"/home/user401/gopath:/google/gopath":{"goroot":"/usr/local/go","version":"1.17.2"}},"goplsSurveyConfig":"{\"prompt\":true,\"promptThisMonth\":false,\"dateComputedPromptThisMonth\":\"2021-11-11T07:12:02.356Z\"}"}}
